{
  "resolvedId": "/home/saeed/w/projects/beautymap/beautyfront/components/icons/PasswordIcon.vue",
  "transforms": [
    {
      "name": "vite:load-fallback",
      "result": "<script setup lang=\"ts\">\r\n\r\n</script>\r\n\r\n<template>\r\n  <svg width=\"25\" height=\"24\" viewBox=\"0 0 25 24\" fill=\"none\" xmlns=\"http://www.w3.org/2000/svg\">\r\n    <path d=\"M2.5 19V17H22.5V19H2.5ZM3.65 12.95L2.35 12.2L3.2 10.7H1.5V9.2H3.2L2.35 7.75L3.65 7L4.5 8.45L5.35 7L6.65 7.75L5.8 9.2H7.5V10.7H5.8L6.65 12.2L5.35 12.95L4.5 11.45L3.65 12.95ZM11.65 12.95L10.35 12.2L11.2 10.7H9.5V9.2H11.2L10.35 7.75L11.65 7L12.5 8.45L13.35 7L14.65 7.75L13.8 9.2H15.5V10.7H13.8L14.65 12.2L13.35 12.95L12.5 11.45L11.65 12.95ZM19.65 12.95L18.35 12.2L19.2 10.7H17.5V9.2H19.2L18.35 7.75L19.65 7L20.5 8.45L21.35 7L22.65 7.75L21.8 9.2H23.5V10.7H21.8L22.65 12.2L21.35 12.95L20.5 11.45L19.65 12.95Z\" fill=\"#A9A7A7\"/>\r\n  </svg>\r\n</template>\r\n\r\n<style scoped>\r\n\r\n</style>",
      "start": 1726490134651,
      "end": 1726490134684,
      "sourcemaps": null
    },
    {
      "name": "nuxt:layer-aliasing",
      "start": 1726490134684,
      "end": 1726490134684,
      "order": "pre"
    },
    {
      "name": "nuxt:server-devonly:transform",
      "start": 1726490134684,
      "end": 1726490134684,
      "order": "pre"
    },
    {
      "name": "nuxt:client-fallback-auto-id",
      "start": 1726490134684,
      "end": 1726490134684,
      "order": "pre"
    },
    {
      "name": "vite:css",
      "start": 1726490134684,
      "end": 1726490134684,
      "order": "normal"
    },
    {
      "name": "vite:esbuild",
      "start": 1726490134684,
      "end": 1726490134684,
      "order": "normal"
    },
    {
      "name": "vite:json",
      "start": 1726490134684,
      "end": 1726490134684,
      "order": "normal"
    },
    {
      "name": "vite:worker",
      "start": 1726490134684,
      "end": 1726490134684,
      "order": "normal"
    },
    {
      "name": "vite:vue",
      "result": "const _sfc_main = {}\nimport { createElementVNode as _createElementVNode, openBlock as _openBlock, createElementBlock as _createElementBlock } from \"vue\"\n\nconst _hoisted_1 = {\n  width: \"25\",\n  height: \"24\",\n  viewBox: \"0 0 25 24\",\n  fill: \"none\",\n  xmlns: \"http://www.w3.org/2000/svg\"\n}\nconst _hoisted_2 = /*#__PURE__*/_createElementVNode(\"path\", {\n  d: \"M2.5 19V17H22.5V19H2.5ZM3.65 12.95L2.35 12.2L3.2 10.7H1.5V9.2H3.2L2.35 7.75L3.65 7L4.5 8.45L5.35 7L6.65 7.75L5.8 9.2H7.5V10.7H5.8L6.65 12.2L5.35 12.95L4.5 11.45L3.65 12.95ZM11.65 12.95L10.35 12.2L11.2 10.7H9.5V9.2H11.2L10.35 7.75L11.65 7L12.5 8.45L13.35 7L14.65 7.75L13.8 9.2H15.5V10.7H13.8L14.65 12.2L13.35 12.95L12.5 11.45L11.65 12.95ZM19.65 12.95L18.35 12.2L19.2 10.7H17.5V9.2H19.2L18.35 7.75L19.65 7L20.5 8.45L21.35 7L22.65 7.75L21.8 9.2H23.5V10.7H21.8L22.65 12.2L21.35 12.95L20.5 11.45L19.65 12.95Z\",\n  fill: \"#A9A7A7\"\n}, null, -1)\nconst _hoisted_3 = [\n  _hoisted_2\n]\n\nfunction _sfc_render(_ctx, _cache) {\n  return (_openBlock(), _createElementBlock(\"svg\", _hoisted_1, _hoisted_3))\n}\n\n\nimport _export_sfc from '\u0000plugin-vue:export-helper'\nexport default /*#__PURE__*/_export_sfc(_sfc_main, [['render',_sfc_render]])",
      "start": 1726490134684,
      "end": 1726490134684,
      "order": "normal",
      "sourcemaps": {
        "mappings": ""
      }
    },
    {
      "name": "vite:vue-jsx",
      "start": 1726490134684,
      "end": 1726490134684,
      "order": "normal"
    },
    {
      "name": "replace",
      "start": 1726490134684,
      "end": 1726490134684,
      "order": "normal"
    },
    {
      "name": "nuxt:remove-plugin-metadata",
      "start": 1726490134684,
      "end": 1726490134684,
      "order": "normal"
    },
    {
      "name": "nuxt:chunk-error",
      "start": 1726490134684,
      "end": 1726490134684,
      "order": "normal"
    },
    {
      "name": "nuxt:components:imports",
      "start": 1726490134684,
      "end": 1726490134684,
      "order": "normal"
    },
    {
      "name": "replace",
      "start": 1726490134684,
      "end": 1726490134684,
      "order": "normal"
    },
    {
      "name": "ssr-styles",
      "start": 1726490134684,
      "end": 1726490134684,
      "order": "normal"
    },
    {
      "name": "vite:define",
      "start": 1726490134684,
      "end": 1726490134684,
      "order": "normal"
    },
    {
      "name": "vite:css-post",
      "start": 1726490134684,
      "end": 1726490134684,
      "order": "normal"
    },
    {
      "name": "vite:build-html",
      "start": 1726490134684,
      "end": 1726490134684,
      "order": "normal"
    },
    {
      "name": "vite:worker-import-meta-url",
      "start": 1726490134684,
      "end": 1726490134684,
      "order": "normal"
    },
    {
      "name": "vite:asset-import-meta-url",
      "start": 1726490134684,
      "end": 1726490134684,
      "order": "normal"
    },
    {
      "name": "commonjs",
      "start": 1726490134684,
      "end": 1726490134684,
      "order": "normal"
    },
    {
      "name": "vite:dynamic-import-vars",
      "start": 1726490134684,
      "end": 1726490134684,
      "order": "normal"
    },
    {
      "name": "vite:import-glob",
      "start": 1726490134684,
      "end": 1726490134684,
      "order": "normal"
    },
    {
      "name": "nuxt:composable-keys",
      "start": 1726490134684,
      "end": 1726490134684,
      "order": "post"
    },
    {
      "name": "nuxt:imports-transform",
      "start": 1726490134684,
      "end": 1726490134684,
      "order": "post"
    },
    {
      "name": "unctx:transform",
      "start": 1726490134684,
      "end": 1726490134685,
      "order": "post"
    },
    {
      "name": "nuxt:pages-macros-transform",
      "start": 1726490134685,
      "end": 1726490134685,
      "order": "post"
    },
    {
      "name": "nuxt:runtime-paths-dep",
      "start": 1726490134685,
      "end": 1726490134685,
      "order": "post"
    },
    {
      "name": "nuxt:route-injection-plugin",
      "start": 1726490134685,
      "end": 1726490134685,
      "order": "post"
    },
    {
      "name": "nuxt:components-loader",
      "start": 1726490134685,
      "end": 1726490134685,
      "order": "post"
    },
    {
      "name": "nuxt:tree-shake-composables:transform",
      "start": 1726490134685,
      "end": 1726490134685,
      "order": "post"
    },
    {
      "name": "vite:build-import-analysis",
      "start": 1726490134685,
      "end": 1726490134685,
      "order": "normal"
    },
    {
      "name": "vite:reporter",
      "start": 1726490134685,
      "end": 1726490134685,
      "order": "normal"
    }
  ]
}
