{
  "resolvedId": "/home/saeed/w/projects/beautymap/beautyfront/components/set-new-password-drawer/SetPasswordForm.vue?vue&type=script&setup=true&lang.ts",
  "transforms": [
    {
      "name": "vite:vue",
      "result": "import { defineComponent as _defineComponent } from 'vue'\nimport { unref as _unref, createVNode as _createVNode, openBlock as _openBlock, createElementBlock as _createElementBlock, createCommentVNode as _createCommentVNode, withCtx as _withCtx } from \"vue\"\n\nconst _hoisted_1 = { class: \"w-full overflow-y-auto\" }\nconst _hoisted_2 = {\n  key: 0,\n  class: \"text-white text-center text-[14px] leading-[21px]\"\n}\nconst _hoisted_3 = {\n  key: 1,\n  class: \"text-white text-center text-[14px] leading-[21px]\"\n}\n\nimport PasswordInput from \"~/components/input/PasswordInput.vue\";\r\nimport MainActionButton from \"~/components/button/form/MainActionButton.vue\";\r\nimport {useDrawerStore} from \"~/store/Drawer\";\r\nimport {useCustomFetch} from \"~/composables/useCustomFetch\";\r\nimport MoonLoader from \"vue-spinner/src/MoonLoader.vue\";\r\n\r\n\nexport default /*#__PURE__*/_defineComponent({\n  __name: 'SetPasswordForm',\n  setup(__props) {\n\r\n\r\nconst store = useDrawerStore()\r\nconst auth = useSanctumAuth()\r\n\r\nconst form = ref<ISetNewPasswordForm>({\r\n  old_password: '',\r\n  password: '',\r\n  password_confirmation: '',\r\n})\r\n\r\nconst pendingValue = ref<Boolean>(false)\r\n\r\nconst doSetPassword = async () => {\r\n  const res = await useCustomFetch('/own/password', {\r\n    method: \"PUT\",\r\n    body: form.value,\r\n  })\r\n  pendingValue.value = true\r\n  if (res.error.value) {\r\n    setTimeout(() => {\r\n      pendingValue.value = false\r\n    }, 500)\r\n  }\r\n  if (res.data.value) {\r\n    setTimeout(() => {\r\n      pendingValue.value = false\r\n      store.closeAllDrawers()\r\n    }, 500)\r\n  }\r\n}\r\n\r\n\nreturn (_ctx: any,_cache: any) => {\n  return (_openBlock(), _createElementBlock(\"div\", _hoisted_1, [\n    _createVNode(PasswordInput, {\n      title: \"کلمه عبور\",\n      modelValue: _unref(form).old_password,\n      \"onUpdate:modelValue\": _cache[0] || (_cache[0] = ($event: any) => ((_unref(form).old_password) = $event)),\n      class: \"mt-[27px]\"\n    }, null, 8, [\"modelValue\"]),\n    _createVNode(PasswordInput, {\n      title: \"کلمه عبور جدید\",\n      modelValue: _unref(form).password,\n      \"onUpdate:modelValue\": _cache[1] || (_cache[1] = ($event: any) => ((_unref(form).password) = $event)),\n      class: \"mt-[27px]\"\n    }, null, 8, [\"modelValue\"]),\n    _createVNode(PasswordInput, {\n      title: \"تکرار کلمه عبور جدید\",\n      modelValue: _unref(form).password_confirmation,\n      \"onUpdate:modelValue\": _cache[2] || (_cache[2] = ($event: any) => ((_unref(form).password_confirmation) = $event)),\n      class: \"mt-[27px]\"\n    }, null, 8, [\"modelValue\"]),\n    _createVNode(MainActionButton, {\n      class: \"mt-[48px] h-[44px]\",\n      onClick: doSetPassword\n    }, {\n      default: _withCtx(() => [\n        (!_unref(pendingValue))\n          ? (_openBlock(), _createElementBlock(\"div\", _hoisted_2, \" بازنشانی رمز عبور \"))\n          : (_openBlock(), _createElementBlock(\"div\", _hoisted_3, [\n              _createVNode(MoonLoader, {\n                loading: true,\n                color: '#fff',\n                size: '25px',\n                margin: \"10px\"\n              })\n            ]))\n      ]),\n      _: 1\n    })\n  ]))\n}\n}\n\n})",
      "start": 1726490134166,
      "end": 1726490134166
    },
    {
      "name": "nuxt:layer-aliasing",
      "start": 1726490134166,
      "end": 1726490134166,
      "order": "pre"
    },
    {
      "name": "nuxt:server-devonly:transform",
      "start": 1726490134166,
      "end": 1726490134166,
      "order": "pre"
    },
    {
      "name": "nuxt:client-fallback-auto-id",
      "start": 1726490134166,
      "end": 1726490134166,
      "order": "pre"
    },
    {
      "name": "vite:css",
      "start": 1726490134166,
      "end": 1726490134166,
      "order": "normal"
    },
    {
      "name": "vite:esbuild",
      "result": "import { defineComponent as _defineComponent } from \"vue\";\nimport { unref as _unref, createVNode as _createVNode, openBlock as _openBlock, createElementBlock as _createElementBlock, withCtx as _withCtx } from \"vue\";\nconst _hoisted_1 = { class: \"w-full overflow-y-auto\" };\nconst _hoisted_2 = {\n  key: 0,\n  class: \"text-white text-center text-[14px] leading-[21px]\"\n};\nconst _hoisted_3 = {\n  key: 1,\n  class: \"text-white text-center text-[14px] leading-[21px]\"\n};\nimport PasswordInput from \"~/components/input/PasswordInput.vue\";\nimport MainActionButton from \"~/components/button/form/MainActionButton.vue\";\nimport { useDrawerStore } from \"~/store/Drawer\";\nimport { useCustomFetch } from \"~/composables/useCustomFetch\";\nimport MoonLoader from \"vue-spinner/src/MoonLoader.vue\";\nexport default /* @__PURE__ */ _defineComponent({\n  __name: \"SetPasswordForm\",\n  setup(__props) {\n    const store = useDrawerStore();\n    const auth = useSanctumAuth();\n    const form = ref({\n      old_password: \"\",\n      password: \"\",\n      password_confirmation: \"\"\n    });\n    const pendingValue = ref(false);\n    const doSetPassword = async () => {\n      const res = await useCustomFetch(\"/own/password\", {\n        method: \"PUT\",\n        body: form.value\n      });\n      pendingValue.value = true;\n      if (res.error.value) {\n        setTimeout(() => {\n          pendingValue.value = false;\n        }, 500);\n      }\n      if (res.data.value) {\n        setTimeout(() => {\n          pendingValue.value = false;\n          store.closeAllDrawers();\n        }, 500);\n      }\n    };\n    return (_ctx, _cache) => {\n      return _openBlock(), _createElementBlock(\"div\", _hoisted_1, [\n        _createVNode(PasswordInput, {\n          title: \"کلمه عبور\",\n          modelValue: _unref(form).old_password,\n          \"onUpdate:modelValue\": _cache[0] || (_cache[0] = ($event) => _unref(form).old_password = $event),\n          class: \"mt-[27px]\"\n        }, null, 8, [\"modelValue\"]),\n        _createVNode(PasswordInput, {\n          title: \"کلمه عبور جدید\",\n          modelValue: _unref(form).password,\n          \"onUpdate:modelValue\": _cache[1] || (_cache[1] = ($event) => _unref(form).password = $event),\n          class: \"mt-[27px]\"\n        }, null, 8, [\"modelValue\"]),\n        _createVNode(PasswordInput, {\n          title: \"تکرار کلمه عبور جدید\",\n          modelValue: _unref(form).password_confirmation,\n          \"onUpdate:modelValue\": _cache[2] || (_cache[2] = ($event) => _unref(form).password_confirmation = $event),\n          class: \"mt-[27px]\"\n        }, null, 8, [\"modelValue\"]),\n        _createVNode(MainActionButton, {\n          class: \"mt-[48px] h-[44px]\",\n          onClick: doSetPassword\n        }, {\n          default: _withCtx(() => [\n            !_unref(pendingValue) ? (_openBlock(), _createElementBlock(\"div\", _hoisted_2, \" بازنشانی رمز عبور \")) : (_openBlock(), _createElementBlock(\"div\", _hoisted_3, [\n              _createVNode(MoonLoader, {\n                loading: true,\n                color: \"#fff\",\n                size: \"25px\",\n                margin: \"10px\"\n              })\n            ]))\n          ]),\n          _: 1\n        })\n      ]);\n    };\n  }\n});\n",
      "start": 1726490134166,
      "end": 1726490134202,
      "order": "normal",
      "sourcemaps": {
        "version": 3,
        "sources": [
          "/home/saeed/w/projects/beautymap/beautyfront/components/set-new-password-drawer/SetPasswordForm.vue?vue&type=script&setup=true&lang.ts"
        ],
        "sourcesContent": [
          "import { defineComponent as _defineComponent } from 'vue'\nimport { unref as _unref, createVNode as _createVNode, openBlock as _openBlock, createElementBlock as _createElementBlock, createCommentVNode as _createCommentVNode, withCtx as _withCtx } from \"vue\"\n\nconst _hoisted_1 = { class: \"w-full overflow-y-auto\" }\nconst _hoisted_2 = {\n  key: 0,\n  class: \"text-white text-center text-[14px] leading-[21px]\"\n}\nconst _hoisted_3 = {\n  key: 1,\n  class: \"text-white text-center text-[14px] leading-[21px]\"\n}\n\nimport PasswordInput from \"~/components/input/PasswordInput.vue\";\r\nimport MainActionButton from \"~/components/button/form/MainActionButton.vue\";\r\nimport {useDrawerStore} from \"~/store/Drawer\";\r\nimport {useCustomFetch} from \"~/composables/useCustomFetch\";\r\nimport MoonLoader from \"vue-spinner/src/MoonLoader.vue\";\r\n\r\n\nexport default /*#__PURE__*/_defineComponent({\n  __name: 'SetPasswordForm',\n  setup(__props) {\n\r\n\r\nconst store = useDrawerStore()\r\nconst auth = useSanctumAuth()\r\n\r\nconst form = ref<ISetNewPasswordForm>({\r\n  old_password: '',\r\n  password: '',\r\n  password_confirmation: '',\r\n})\r\n\r\nconst pendingValue = ref<Boolean>(false)\r\n\r\nconst doSetPassword = async () => {\r\n  const res = await useCustomFetch('/own/password', {\r\n    method: \"PUT\",\r\n    body: form.value,\r\n  })\r\n  pendingValue.value = true\r\n  if (res.error.value) {\r\n    setTimeout(() => {\r\n      pendingValue.value = false\r\n    }, 500)\r\n  }\r\n  if (res.data.value) {\r\n    setTimeout(() => {\r\n      pendingValue.value = false\r\n      store.closeAllDrawers()\r\n    }, 500)\r\n  }\r\n}\r\n\r\n\nreturn (_ctx: any,_cache: any) => {\n  return (_openBlock(), _createElementBlock(\"div\", _hoisted_1, [\n    _createVNode(PasswordInput, {\n      title: \"کلمه عبور\",\n      modelValue: _unref(form).old_password,\n      \"onUpdate:modelValue\": _cache[0] || (_cache[0] = ($event: any) => ((_unref(form).old_password) = $event)),\n      class: \"mt-[27px]\"\n    }, null, 8, [\"modelValue\"]),\n    _createVNode(PasswordInput, {\n      title: \"کلمه عبور جدید\",\n      modelValue: _unref(form).password,\n      \"onUpdate:modelValue\": _cache[1] || (_cache[1] = ($event: any) => ((_unref(form).password) = $event)),\n      class: \"mt-[27px]\"\n    }, null, 8, [\"modelValue\"]),\n    _createVNode(PasswordInput, {\n      title: \"تکرار کلمه عبور جدید\",\n      modelValue: _unref(form).password_confirmation,\n      \"onUpdate:modelValue\": _cache[2] || (_cache[2] = ($event: any) => ((_unref(form).password_confirmation) = $event)),\n      class: \"mt-[27px]\"\n    }, null, 8, [\"modelValue\"]),\n    _createVNode(MainActionButton, {\n      class: \"mt-[48px] h-[44px]\",\n      onClick: doSetPassword\n    }, {\n      default: _withCtx(() => [\n        (!_unref(pendingValue))\n          ? (_openBlock(), _createElementBlock(\"div\", _hoisted_2, \" بازنشانی رمز عبور \"))\n          : (_openBlock(), _createElementBlock(\"div\", _hoisted_3, [\n              _createVNode(MoonLoader, {\n                loading: true,\n                color: '#fff',\n                size: '25px',\n                margin: \"10px\"\n              })\n            ]))\n      ]),\n      _: 1\n    })\n  ]))\n}\n}\n\n})"
        ],
        "mappings": "AAAA,SAAS,mBAAmB,wBAAwB;AACpD,SAAS,SAAS,QAAQ,eAAe,cAAc,aAAa,YAAY,sBAAsB,qBAAgE,WAAW,gBAAgB;AAEjM,MAAM,aAAa,EAAE,OAAO,yBAAyB;AACrD,MAAM,aAAa;AAAA,EACjB,KAAK;AAAA,EACL,OAAO;AACT;AACA,MAAM,aAAa;AAAA,EACjB,KAAK;AAAA,EACL,OAAO;AACT;AAEA,OAAO,mBAAmB;AAC1B,OAAO,sBAAsB;AAC7B,SAAQ,sBAAqB;AAC7B,SAAQ,sBAAqB;AAC7B,OAAO,gBAAgB;AAGvB,eAA4B,iCAAiB;AAAA,EAC3C,QAAQ;AAAA,EACR,MAAM,SAAS;AAGjB,UAAM,QAAQ,eAAe;AAC7B,UAAM,OAAO,eAAe;AAE5B,UAAM,OAAO,IAAyB;AAAA,MACpC,cAAc;AAAA,MACd,UAAU;AAAA,MACV,uBAAuB;AAAA,IACzB,CAAC;AAED,UAAM,eAAe,IAAa,KAAK;AAEvC,UAAM,gBAAgB,YAAY;AAChC,YAAM,MAAM,MAAM,eAAe,iBAAiB;AAAA,QAChD,QAAQ;AAAA,QACR,MAAM,KAAK;AAAA,MACb,CAAC;AACD,mBAAa,QAAQ;AACrB,UAAI,IAAI,MAAM,OAAO;AACnB,mBAAW,MAAM;AACf,uBAAa,QAAQ;AAAA,QACvB,GAAG,GAAG;AAAA,MACR;AACA,UAAI,IAAI,KAAK,OAAO;AAClB,mBAAW,MAAM;AACf,uBAAa,QAAQ;AACrB,gBAAM,gBAAgB;AAAA,QACxB,GAAG,GAAG;AAAA,MACR;AAAA,IACF;AAGA,WAAO,CAAC,MAAU,WAAgB;AAChC,aAAQ,WAAW,GAAG,oBAAoB,OAAO,YAAY;AAAA,QAC3D,aAAa,eAAe;AAAA,UAC1B,OAAO;AAAA,UACP,YAAY,OAAO,IAAI,EAAE;AAAA,UACzB,uBAAuB,OAAO,CAAC,MAAM,OAAO,CAAC,IAAI,CAAC,WAAkB,OAAO,IAAI,EAAE,eAAgB;AAAA,UACjG,OAAO;AAAA,QACT,GAAG,MAAM,GAAG,CAAC,YAAY,CAAC;AAAA,QAC1B,aAAa,eAAe;AAAA,UAC1B,OAAO;AAAA,UACP,YAAY,OAAO,IAAI,EAAE;AAAA,UACzB,uBAAuB,OAAO,CAAC,MAAM,OAAO,CAAC,IAAI,CAAC,WAAkB,OAAO,IAAI,EAAE,WAAY;AAAA,UAC7F,OAAO;AAAA,QACT,GAAG,MAAM,GAAG,CAAC,YAAY,CAAC;AAAA,QAC1B,aAAa,eAAe;AAAA,UAC1B,OAAO;AAAA,UACP,YAAY,OAAO,IAAI,EAAE;AAAA,UACzB,uBAAuB,OAAO,CAAC,MAAM,OAAO,CAAC,IAAI,CAAC,WAAkB,OAAO,IAAI,EAAE,wBAAyB;AAAA,UAC1G,OAAO;AAAA,QACT,GAAG,MAAM,GAAG,CAAC,YAAY,CAAC;AAAA,QAC1B,aAAa,kBAAkB;AAAA,UAC7B,OAAO;AAAA,UACP,SAAS;AAAA,QACX,GAAG;AAAA,UACD,SAAS,SAAS,MAAM;AAAA,YACrB,CAAC,OAAO,YAAY,KAChB,WAAW,GAAG,oBAAoB,OAAO,YAAY,qBAAqB,MAC1E,WAAW,GAAG,oBAAoB,OAAO,YAAY;AAAA,cACpD,aAAa,YAAY;AAAA,gBACvB,SAAS;AAAA,gBACT,OAAO;AAAA,gBACP,MAAM;AAAA,gBACN,QAAQ;AAAA,cACV,CAAC;AAAA,YACH,CAAC;AAAA,UACP,CAAC;AAAA,UACD,GAAG;AAAA,QACL,CAAC;AAAA,MACH,CAAC;AAAA,IACH;AAAA,EACA;AAEA,CAAC;",
        "names": []
      }
    },
    {
      "name": "vite:json",
      "start": 1726490134202,
      "end": 1726490134202,
      "order": "normal"
    },
    {
      "name": "vite:worker",
      "start": 1726490134202,
      "end": 1726490134202,
      "order": "normal"
    },
    {
      "name": "vite:vue",
      "start": 1726490134202,
      "end": 1726490134202,
      "order": "normal"
    },
    {
      "name": "vite:vue-jsx",
      "start": 1726490134202,
      "end": 1726490134202,
      "order": "normal"
    },
    {
      "name": "replace",
      "start": 1726490134202,
      "end": 1726490134202,
      "order": "normal"
    },
    {
      "name": "nuxt:remove-plugin-metadata",
      "start": 1726490134202,
      "end": 1726490134202,
      "order": "normal"
    },
    {
      "name": "nuxt:chunk-error",
      "start": 1726490134202,
      "end": 1726490134202,
      "order": "normal"
    },
    {
      "name": "nuxt:components:imports",
      "start": 1726490134202,
      "end": 1726490134202,
      "order": "normal"
    },
    {
      "name": "replace",
      "start": 1726490134202,
      "end": 1726490134202,
      "order": "normal"
    },
    {
      "name": "ssr-styles",
      "start": 1726490134202,
      "end": 1726490134202,
      "order": "normal"
    },
    {
      "name": "vite:define",
      "start": 1726490134202,
      "end": 1726490134202,
      "order": "normal"
    },
    {
      "name": "vite:css-post",
      "start": 1726490134202,
      "end": 1726490134202,
      "order": "normal"
    },
    {
      "name": "vite:build-html",
      "start": 1726490134202,
      "end": 1726490134202,
      "order": "normal"
    },
    {
      "name": "vite:worker-import-meta-url",
      "start": 1726490134203,
      "end": 1726490134203,
      "order": "normal"
    },
    {
      "name": "vite:asset-import-meta-url",
      "start": 1726490134203,
      "end": 1726490134203,
      "order": "normal"
    },
    {
      "name": "commonjs",
      "start": 1726490134203,
      "end": 1726490134203,
      "order": "normal"
    },
    {
      "name": "vite:dynamic-import-vars",
      "start": 1726490134203,
      "end": 1726490134203,
      "order": "normal"
    },
    {
      "name": "vite:import-glob",
      "start": 1726490134203,
      "end": 1726490134203,
      "order": "normal"
    },
    {
      "name": "nuxt:composable-keys",
      "start": 1726490134203,
      "end": 1726490134203,
      "order": "post"
    },
    {
      "name": "nuxt:imports-transform",
      "result": "import { useSanctumAuth } from '/home/saeed/w/projects/beautymap/beautyfront/node_modules/nuxt-auth-sanctum/dist/runtime/composables/useSanctumAuth.mjs';\nimport { ref } from 'vue';\nimport { defineComponent as _defineComponent } from \"vue\";\nimport { unref as _unref, createVNode as _createVNode, openBlock as _openBlock, createElementBlock as _createElementBlock, withCtx as _withCtx } from \"vue\";\nconst _hoisted_1 = { class: \"w-full overflow-y-auto\" };\nconst _hoisted_2 = {\n  key: 0,\n  class: \"text-white text-center text-[14px] leading-[21px]\"\n};\nconst _hoisted_3 = {\n  key: 1,\n  class: \"text-white text-center text-[14px] leading-[21px]\"\n};\nimport PasswordInput from \"~/components/input/PasswordInput.vue\";\nimport MainActionButton from \"~/components/button/form/MainActionButton.vue\";\nimport { useDrawerStore } from \"~/store/Drawer\";\nimport { useCustomFetch } from \"~/composables/useCustomFetch\";\nimport MoonLoader from \"vue-spinner/src/MoonLoader.vue\";\nexport default /* @__PURE__ */ _defineComponent({\n  __name: \"SetPasswordForm\",\n  setup(__props) {\n    const store = useDrawerStore();\n    const auth = useSanctumAuth();\n    const form = ref({\n      old_password: \"\",\n      password: \"\",\n      password_confirmation: \"\"\n    });\n    const pendingValue = ref(false);\n    const doSetPassword = async () => {\n      const res = await useCustomFetch(\"/own/password\", {\n        method: \"PUT\",\n        body: form.value\n      });\n      pendingValue.value = true;\n      if (res.error.value) {\n        setTimeout(() => {\n          pendingValue.value = false;\n        }, 500);\n      }\n      if (res.data.value) {\n        setTimeout(() => {\n          pendingValue.value = false;\n          store.closeAllDrawers();\n        }, 500);\n      }\n    };\n    return (_ctx, _cache) => {\n      return _openBlock(), _createElementBlock(\"div\", _hoisted_1, [\n        _createVNode(PasswordInput, {\n          title: \"کلمه عبور\",\n          modelValue: _unref(form).old_password,\n          \"onUpdate:modelValue\": _cache[0] || (_cache[0] = ($event) => _unref(form).old_password = $event),\n          class: \"mt-[27px]\"\n        }, null, 8, [\"modelValue\"]),\n        _createVNode(PasswordInput, {\n          title: \"کلمه عبور جدید\",\n          modelValue: _unref(form).password,\n          \"onUpdate:modelValue\": _cache[1] || (_cache[1] = ($event) => _unref(form).password = $event),\n          class: \"mt-[27px]\"\n        }, null, 8, [\"modelValue\"]),\n        _createVNode(PasswordInput, {\n          title: \"تکرار کلمه عبور جدید\",\n          modelValue: _unref(form).password_confirmation,\n          \"onUpdate:modelValue\": _cache[2] || (_cache[2] = ($event) => _unref(form).password_confirmation = $event),\n          class: \"mt-[27px]\"\n        }, null, 8, [\"modelValue\"]),\n        _createVNode(MainActionButton, {\n          class: \"mt-[48px] h-[44px]\",\n          onClick: doSetPassword\n        }, {\n          default: _withCtx(() => [\n            !_unref(pendingValue) ? (_openBlock(), _createElementBlock(\"div\", _hoisted_2, \" بازنشانی رمز عبور \")) : (_openBlock(), _createElementBlock(\"div\", _hoisted_3, [\n              _createVNode(MoonLoader, {\n                loading: true,\n                color: \"#fff\",\n                size: \"25px\",\n                margin: \"10px\"\n              })\n            ]))\n          ]),\n          _: 1\n        })\n      ]);\n    };\n  }\n});\n",
      "start": 1726490134203,
      "end": 1726490134212,
      "order": "post",
      "sourcemaps": {
        "version": 3,
        "sources": [
          ""
        ],
        "names": [],
        "mappings": ";;AAAA,CAAC,CAAC,CAAC,CAAC,CAAC,CAAC,CAAC,CAAC,CAAC,CAAC,CAAC,CAAC,CAAC,CAAC,CAAC,CAAC,CAAC,CAAC,CAAC,CAAC,CAAC,CAAC,CAAC,CAAC,CAAC,CAAC,CAAC,CAAC,CAAC,CAAC,CAAC,CAAC,CAAC,CAAC,CAAC,CAAC,CAAC,CAAC,CAAC,CAAC,CAAC,CAAC,CAAC,CAAC,CAAC,CAAC,CAAC,CAAC,CAAC,CAAC,CAAC,CAAC,CAAC,CAAC,CAAC,CAAC,CAAC,CAAC;AAC1D,CAAC,CAAC,CAAC,CAAC,CAAC,CAAC,CAAC,CAAC,CAAC,CAAC,CAAC,CAAC,CAAC,CAAC,CAAC,CAAC,CAAC,CAAC,CAAC,CAAC,CAAC,CAAC,CAAC,CAAC,CAAC,CAAC,CAAC,CAAC,CAAC,CAAC,CAAC,CAAC,CAAC,CAAC,CAAC,CAAC,CAAC,CAAC,CAAC,CAAC,CAAC,CAAC,CAAC,CAAC,CAAC,CAAC,CAAC,CAAC,CAAC,CAAC,CAAC,CAAC,CAAC,CAAC,CAAC,CAAC,CAAC,CAAC,CAAC,CAAC,CAAC,CAAC,CAAC,CAAC,CAAC,CAAC,CAAC,CAAC,CAAC,CAAC,CAAC,CAAC,CAAC,CAAC,CAAC,CAAC,CAAC,CAAC,CAAC,CAAC,CAAC,CAAC,CAAC,CAAC,CAAC,CAAC,CAAC,CAAC,CAAC,CAAC,CAAC,CAAC,CAAC,CAAC,CAAC,CAAC,CAAC,CAAC,CAAC,CAAC,CAAC,CAAC,CAAC,CAAC,CAAC,CAAC,CAAC,CAAC,CAAC,CAAC,CAAC,CAAC,CAAC,CAAC,CAAC,CAAC,CAAC,CAAC,CAAC,CAAC,CAAC,CAAC,CAAC,CAAC,CAAC,CAAC,CAAC,CAAC,CAAC,CAAC,CAAC,CAAC,CAAC,CAAC,CAAC,CAAC,CAAC,CAAC,CAAC,CAAC,CAAC,CAAC,CAAC,CAAC,CAAC,CAAC,CAAC,CAAC,CAAC,CAAC,CAAC,CAAC,CAAC,CAAC,CAAC,CAAC;AAC5J,CAAC,CAAC,CAAC,CAAC,CAAC,CAAC,CAAC,CAAC,CAAC,CAAC,CAAC,CAAC,CAAC,CAAC,CAAC,CAAC,CAAC,CAAC,CAAC,CAAC,CAAC,CAAC,CAAC,CAAC,CAAC,CAAC,CAAC,CAAC,CAAC,CAAC,CAAC,CAAC,CAAC,CAAC,CAAC,CAAC,CAAC,CAAC,CAAC,CAAC,CAAC,CAAC,CAAC,CAAC,CAAC,CAAC,CAAC,CAAC,CAAC,CAAC,CAAC,CAAC,CAAC,CAAC,CAAC;AACvD,CAAC,CAAC,CAAC,CAAC,CAAC,CAAC,CAAC,CAAC,CAAC,CAAC,CAAC,CAAC,CAAC,CAAC,CAAC,CAAC,CAAC,CAAC,CAAC,CAAC;AACpB,CAAC,CAAC,CAAC,CAAC,CAAC,CAAC,CAAC,CAAC,CAAC;AACT,CAAC,CAAC,CAAC,CAAC,CAAC,CAAC,CAAC,CAAC,CAAC,CAAC,CAAC,CAAC,CAAC,CAAC,CAAC,CAAC,CAAC,CAAC,CAAC,CAAC,CAAC,CAAC,CAAC,CAAC,CAAC,CAAC,CAAC,CAAC,CAAC,CAAC,CAAC,CAAC,CAAC,CAAC,CAAC,CAAC,CAAC,CAAC,CAAC,CAAC,CAAC,CAAC,CAAC,CAAC,CAAC,CAAC,CAAC,CAAC,CAAC,CAAC,CAAC,CAAC,CAAC,CAAC,CAAC,CAAC,CAAC,CAAC,CAAC,CAAC;AAC5D,CAAC,CAAC;AACF,CAAC,CAAC,CAAC,CAAC,CAAC,CAAC,CAAC,CAAC,CAAC,CAAC,CAAC,CAAC,CAAC,CAAC,CAAC,CAAC,CAAC,CAAC,CAAC,CAAC;AACpB,CAAC,CAAC,CAAC,CAAC,CAAC,CAAC,CAAC,CAAC,CAAC;AACT,CAAC,CAAC,CAAC,CAAC,CAAC,CAAC,CAAC,CAAC,CAAC,CAAC,CAAC,CAAC,CAAC,CAAC,CAAC,CAAC,CAAC,CAAC,CAAC,CAAC,CAAC,CAAC,CAAC,CAAC,CAAC,CAAC,CAAC,CAAC,CAAC,CAAC,CAAC,CAAC,CAAC,CAAC,CAAC,CAAC,CAAC,CAAC,CAAC,CAAC,CAAC,CAAC,CAAC,CAAC,CAAC,CAAC,CAAC,CAAC,CAAC,CAAC,CAAC,CAAC,CAAC,CAAC,CAAC,CAAC,CAAC,CAAC,CAAC,CAAC;AAC5D,CAAC,CAAC;AACF,CAAC,CAAC,CAAC,CAAC,CAAC,CAAC,CAAC,CAAC,CAAC,CAAC,CAAC,CAAC,CAAC,CAAC,CAAC,CAAC,CAAC,CAAC,CAAC,CAAC,CAAC,CAAC,CAAC,CAAC,CAAC,CAAC,CAAC,CAAC,CAAC,CAAC,CAAC,CAAC,CAAC,CAAC,CAAC,CAAC,CAAC,CAAC,CAAC,CAAC,CAAC,CAAC,CAAC,CAAC,CAAC,CAAC,CAAC,CAAC,CAAC,CAAC,CAAC,CAAC,CAAC,CAAC,CAAC,CAAC,CAAC,CAAC,CAAC,CAAC,CAAC,CAAC,CAAC,CAAC,CAAC;AACjE,CAAC,CAAC,CAAC,CAAC,CAAC,CAAC,CAAC,CAAC,CAAC,CAAC,CAAC,CAAC,CAAC,CAAC,CAAC,CAAC,CAAC,CAAC,CAAC,CAAC,CAAC,CAAC,CAAC,CAAC,CAAC,CAAC,CAAC,CAAC,CAAC,CAAC,CAAC,CAAC,CAAC,CAAC,CAAC,CAAC,CAAC,CAAC,CAAC,CAAC,CAAC,CAAC,CAAC,CAAC,CAAC,CAAC,CAAC,CAAC,CAAC,CAAC,CAAC,CAAC,CAAC,CAAC,CAAC,CAAC,CAAC,CAAC,CAAC,CAAC,CAAC,CAAC,CAAC,CAAC,CAAC,CAAC,CAAC,CAAC,CAAC,CAAC,CAAC,CAAC,CAAC,CAAC,CAAC,CAAC,CAAC;AAC7E,CAAC,CAAC,CAAC,CAAC,CAAC,CAAC,CAAC,CAAC,CAAC,CAAC,CAAC,CAAC,CAAC,CAAC,CAAC,CAAC,CAAC,CAAC,CAAC,CAAC,CAAC,CAAC,CAAC,CAAC,CAAC,CAAC,CAAC,CAAC,CAAC,CAAC,CAAC,CAAC,CAAC,CAAC,CAAC,CAAC,CAAC,CAAC,CAAC,CAAC,CAAC,CAAC,CAAC,CAAC,CAAC,CAAC,CAAC,CAAC;AAChD,CAAC,CAAC,CAAC,CAAC,CAAC,CAAC,CAAC,CAAC,CAAC,CAAC,CAAC,CAAC,CAAC,CAAC,CAAC,CAAC,CAAC,CAAC,CAAC,CAAC,CAAC,CAAC,CAAC,CAAC,CAAC,CAAC,CAAC,CAAC,CAAC,CAAC,CAAC,CAAC,CAAC,CAAC,CAAC,CAAC,CAAC,CAAC,CAAC,CAAC,CAAC,CAAC,CAAC,CAAC,CAAC,CAAC,CAAC,CAAC,CAAC,CAAC,CAAC,CAAC,CAAC,CAAC,CAAC,CAAC,CAAC,CAAC,CAAC,CAAC,CAAC,CAAC;AAC9D,CAAC,CAAC,CAAC,CAAC,CAAC,CAAC,CAAC,CAAC,CAAC,CAAC,CAAC,CAAC,CAAC,CAAC,CAAC,CAAC,CAAC,CAAC,CAAC,CAAC,CAAC,CAAC,CAAC,CAAC,CAAC,CAAC,CAAC,CAAC,CAAC,CAAC,CAAC,CAAC,CAAC,CAAC,CAAC,CAAC,CAAC,CAAC,CAAC,CAAC,CAAC,CAAC,CAAC,CAAC,CAAC,CAAC,CAAC,CAAC,CAAC,CAAC,CAAC,CAAC,CAAC,CAAC,CAAC,CAAC;AACxD,CAAC,CAAC,CAAC,CAAC,CAAC,CAAC,CAAC,CAAC,CAAC,CAAC,CAAC,CAAC,CAAC,CAAC,CAAC,CAAC,CAAC,CAAC,CAAC,CAAC,CAAC,CAAC,CAAC,CAAC,CAAC,CAAC,CAAC,CAAC,CAAC,CAAC,CAAC,CAAC,CAAC,CAAC,CAAC,CAAC,CAAC,CAAC,CAAC,CAAC,CAAC,CAAC,CAAC,CAAC,CAAC,CAAC,CAAC,CAAC,CAAC;AACjD,CAAC,CAAC,CAAC,CAAC,CAAC,CAAC,CAAC,CAAC,CAAC,CAAC,CAAC,CAAC,CAAC,CAAC,CAAC,CAAC,CAAC,CAAC,CAAC,CAAC,CAAC,CAAC,CAAC,CAAC,CAAC,CAAC,CAAC,CAAC;AAC5B,CAAC,CAAC,CAAC,CAAC,CAAC,CAAC,CAAC,CAAC,CAAC,CAAC,CAAC,CAAC,CAAC,CAAC,CAAC,CAAC,CAAC,CAAC;AAClB,CAAC,CAAC,CAAC,CAAC,CAAC,CAAC,CAAC,CAAC,CAAC,CAAC,CAAC,CAAC,CAAC,CAAC,CAAC,CAAC,CAAC,CAAC,CAAC,CAAC,CAAC,CAAC,CAAC,CAAC,CAAC,CAAC,CAAC,CAAC,CAAC,CAAC,CAAC,CAAC,CAAC,CAAC,CAAC;AACnC,CAAC,CAAC,CAAC,CAAC,CAAC,CAAC,CAAC,CAAC,CAAC,CAAC,CAAC,CAAC,CAAC,CAAC,CAAC,CAAC,CAAC,CAAC,CAAC,CAAC,CAAC,CAAC,CAAC,CAAC,CAAC,CAAC,CAAC,CAAC,CAAC,CAAC,CAAC,CAAC,CAAC,CAAC;AAClC,CAAC,CAAC,CAAC,CAAC,CAAC,CAAC,CAAC,CAAC,CAAC,CAAC,CAAC,CAAC,CAAC,CAAC,CAAC,CAAC,CAAC,CAAC,CAAC,CAAC,CAAC,CAAC;AACtB,CAAC,CAAC,CAAC,CAAC,CAAC,CAAC,CAAC,CAAC,CAAC,CAAC,CAAC,CAAC,CAAC,CAAC,CAAC,CAAC,CAAC,CAAC,CAAC,CAAC,CAAC,CAAC,CAAC;AACvB,CAAC,CAAC,CAAC,CAAC,CAAC,CAAC,CAAC,CAAC,CAAC,CAAC,CAAC,CAAC,CAAC,CAAC,CAAC,CAAC,CAAC,CAAC,CAAC;AACnB,CAAC,CAAC,CAAC,CAAC,CAAC,CAAC,CAAC,CAAC,CAAC,CAAC,CAAC,CAAC,CAAC,CAAC,CAAC,CAAC,CAAC,CAAC,CAAC,CAAC,CAAC,CAAC,CAAC,CAAC,CAAC,CAAC,CAAC,CAAC,CAAC,CAAC,CAAC;AAC/B,CAAC,CAAC,CAAC,CAAC,CAAC,CAAC,CAAC;AACP,CAAC,CAAC,CAAC,CAAC,CAAC,CAAC,CAAC,CAAC,CAAC,CAAC,CAAC,CAAC,CAAC,CAAC,CAAC,CAAC,CAAC,CAAC,CAAC,CAAC,CAAC,CAAC,CAAC,CAAC,CAAC,CAAC,CAAC,CAAC,CAAC,CAAC,CAAC,CAAC,CAAC,CAAC,CAAC,CAAC;AACpC,CAAC,CAAC,CAAC,CAAC,CAAC,CAAC,CAAC,CAAC,CAAC,CAAC,CAAC,CAAC,CAAC,CAAC,CAAC,CAAC,CAAC,CAAC,CAAC,CAAC,CAAC,CAAC,CAAC,CAAC,CAAC,CAAC,CAAC,CAAC,CAAC,CAAC,CAAC,CAAC,CAAC,CAAC,CAAC,CAAC,CAAC,CAAC,CAAC;AACvC,CAAC,CAAC,CAAC,CAAC,CAAC,CAAC,CAAC,CAAC,CAAC,CAAC,CAAC,CAAC,CAAC,CAAC,CAAC,CAAC,CAAC,CAAC,CAAC,CAAC,CAAC,CAAC,CAAC,CAAC,CAAC,CAAC,CAAC,CAAC,CAAC,CAAC,CAAC,CAAC,CAAC,CAAC,CAAC,CAAC,CAAC,CAAC,CAAC,CAAC,CAAC,CAAC,CAAC,CAAC,CAAC,CAAC,CAAC,CAAC,CAAC,CAAC,CAAC,CAAC,CAAC,CAAC,CAAC,CAAC,CAAC;AACzD,CAAC,CAAC,CAAC,CAAC,CAAC,CAAC,CAAC,CAAC,CAAC,CAAC,CAAC,CAAC,CAAC,CAAC,CAAC,CAAC,CAAC,CAAC,CAAC,CAAC,CAAC,CAAC;AACtB,CAAC,CAAC,CAAC,CAAC,CAAC,CAAC,CAAC,CAAC,CAAC,CAAC,CAAC,CAAC,CAAC,CAAC,CAAC,CAAC,CAAC,CAAC,CAAC,CAAC,CAAC,CAAC,CAAC,CAAC;AACxB,CAAC,CAAC,CAAC,CAAC,CAAC,CAAC,CAAC,CAAC,CAAC;AACT,CAAC,CAAC,CAAC,CAAC,CAAC,CAAC,CAAC,CAAC,CAAC,CAAC,CAAC,CAAC,CAAC,CAAC,CAAC,CAAC,CAAC,CAAC,CAAC,CAAC,CAAC,CAAC,CAAC,CAAC,CAAC,CAAC,CAAC,CAAC,CAAC,CAAC,CAAC,CAAC;AAChC,CAAC,CAAC,CAAC,CAAC,CAAC,CAAC,CAAC,CAAC,CAAC,CAAC,CAAC,CAAC,CAAC,CAAC,CAAC,CAAC,CAAC,CAAC,CAAC,CAAC,CAAC,CAAC,CAAC,CAAC,CAAC,CAAC,CAAC,CAAC;AAC5B,CAAC,CAAC,CAAC,CAAC,CAAC,CAAC,CAAC,CAAC,CAAC,CAAC,CAAC,CAAC,CAAC,CAAC,CAAC,CAAC,CAAC,CAAC,CAAC,CAAC,CAAC,CAAC,CAAC,CAAC,CAAC,CAAC;AAC1B,CAAC,CAAC,CAAC,CAAC,CAAC,CAAC,CAAC,CAAC,CAAC,CAAC,CAAC,CAAC,CAAC,CAAC,CAAC,CAAC,CAAC,CAAC,CAAC,CAAC,CAAC,CAAC,CAAC,CAAC,CAAC,CAAC,CAAC,CAAC,CAAC,CAAC,CAAC,CAAC,CAAC,CAAC,CAAC,CAAC,CAAC;AACrC,CAAC,CAAC,CAAC,CAAC,CAAC,CAAC,CAAC,CAAC,CAAC,CAAC,CAAC,CAAC,CAAC,CAAC,CAAC,CAAC;AAChB,CAAC,CAAC,CAAC,CAAC,CAAC,CAAC,CAAC;AACP,CAAC,CAAC,CAAC,CAAC,CAAC,CAAC,CAAC,CAAC,CAAC,CAAC,CAAC,CAAC,CAAC,CAAC,CAAC,CAAC,CAAC,CAAC,CAAC,CAAC,CAAC,CAAC,CAAC,CAAC,CAAC,CAAC,CAAC;AAC3B,CAAC,CAAC,CAAC,CAAC,CAAC,CAAC,CAAC,CAAC,CAAC,CAAC,CAAC,CAAC,CAAC,CAAC,CAAC,CAAC,CAAC,CAAC,CAAC,CAAC,CAAC,CAAC,CAAC,CAAC,CAAC,CAAC;AAC1B,CAAC,CAAC,CAAC,CAAC,CAAC,CAAC,CAAC,CAAC,CAAC,CAAC,CAAC,CAAC,CAAC,CAAC,CAAC,CAAC,CAAC,CAAC,CAAC,CAAC,CAAC,CAAC,CAAC,CAAC,CAAC,CAAC,CAAC,CAAC,CAAC,CAAC,CAAC,CAAC,CAAC,CAAC,CAAC,CAAC,CAAC;AACrC,CAAC,CAAC,CAAC,CAAC,CAAC,CAAC,CAAC,CAAC,CAAC,CAAC,CAAC,CAAC,CAAC,CAAC,CAAC,CAAC,CAAC,CAAC,CAAC,CAAC,CAAC,CAAC,CAAC,CAAC,CAAC,CAAC,CAAC,CAAC,CAAC,CAAC,CAAC,CAAC,CAAC,CAAC;AAClC,CAAC,CAAC,CAAC,CAAC,CAAC,CAAC,CAAC,CAAC,CAAC,CAAC,CAAC,CAAC,CAAC,CAAC,CAAC,CAAC;AAChB,CAAC,CAAC,CAAC,CAAC,CAAC,CAAC,CAAC;AACP,CAAC,CAAC,CAAC,CAAC,CAAC,CAAC;AACN,CAAC,CAAC,CAAC,CAAC,CAAC,CAAC,CAAC,CAAC,CAAC,CAAC,CAAC,CAAC,CAAC,CAAC,CAAC,CAAC,CAAC,CAAC,CAAC,CAAC,CAAC,CAAC,CAAC,CAAC,CAAC,CAAC,CAAC,CAAC,CAAC,CAAC;AAC9B,CAAC,CAAC,CAAC,CAAC,CAAC,CAAC,CAAC,CAAC,CAAC,CAAC,CAAC,CAAC,CAAC,CAAC,CAAC,CAAC,CAAC,CAAC,CAAC,CAAC,CAAC,CAAC,CAAC,CAAC,CAAC,CAAC,CAAC,CAAC,CAAC,CAAC,CAAC,CAAC,CAAC,CAAC,CAAC,CAAC,CAAC,CAAC,CAAC,CAAC,CAAC,CAAC,CAAC,CAAC,CAAC,CAAC,CAAC,CAAC,CAAC,CAAC,CAAC,CAAC,CAAC,CAAC,CAAC,CAAC,CAAC,CAAC,CAAC,CAAC,CAAC,CAAC,CAAC,CAAC,CAAC,CAAC,CAAC;AACnE,CAAC,CAAC,CAAC,CAAC,CAAC,CAAC,CAAC,CAAC,CAAC,CAAC,CAAC,CAAC,CAAC,CAAC,CAAC,CAAC,CAAC,CAAC,CAAC,CAAC,CAAC,CAAC,CAAC,CAAC,CAAC,CAAC,CAAC,CAAC,CAAC,CAAC,CAAC,CAAC,CAAC,CAAC,CAAC,CAAC,CAAC;AACrC,CAAC,CAAC,CAAC,CAAC,CAAC,CAAC,CAAC,CAAC,CAAC,CAAC,CAAC,CAAC,CAAC,CAAC,CAAC,CAAC,CAAC,CAAC,CAAC,CAAC,CAAC,CAAC,CAAC,CAAC,CAAC,CAAC,CAAC,CAAC,CAAC;AAC7B,CAAC,CAAC,CAAC,CAAC,CAAC,CAAC,CAAC,CAAC,CAAC,CAAC,CAAC,CAAC,CAAC,CAAC,CAAC,CAAC,CAAC,CAAC,CAAC,CAAC,CAAC,CAAC,CAAC,CAAC,CAAC,CAAC,CAAC,CAAC,CAAC,CAAC,CAAC,CAAC,CAAC,CAAC,CAAC,CAAC,CAAC,CAAC,CAAC,CAAC,CAAC,CAAC,CAAC,CAAC,CAAC,CAAC,CAAC,CAAC;AAChD,CAAC,CAAC,CAAC,CAAC,CAAC,CAAC,CAAC,CAAC,CAAC,CAAC,CAAC,CAAC,CAAC,CAAC,CAAC,CAAC,CAAC,CAAC,CAAC,CAAC,CAAC,CAAC,CAAC,CAAC,CAAC,CAAC,CAAC,CAAC,CAAC,CAAC,CAAC,CAAC,CAAC,CAAC,CAAC,CAAC,CAAC,CAAC,CAAC,CAAC,CAAC,CAAC,CAAC,CAAC,CAAC,CAAC,CAAC,CAAC,CAAC,CAAC,CAAC,CAAC,CAAC,CAAC,CAAC,CAAC,CAAC,CAAC,CAAC,CAAC,CAAC,CAAC,CAAC,CAAC,CAAC,CAAC,CAAC,CAAC,CAAC,CAAC,CAAC,CAAC,CAAC,CAAC,CAAC,CAAC,CAAC,CAAC,CAAC,CAAC,CAAC,CAAC,CAAC,CAAC,CAAC,CAAC,CAAC,CAAC,CAAC,CAAC,CAAC,CAAC,CAAC,CAAC,CAAC,CAAC,CAAC,CAAC,CAAC,CAAC,CAAC,CAAC,CAAC,CAAC,CAAC,CAAC,CAAC;AAC3G,CAAC,CAAC,CAAC,CAAC,CAAC,CAAC,CAAC,CAAC,CAAC,CAAC,CAAC,CAAC,CAAC,CAAC,CAAC,CAAC,CAAC,CAAC,CAAC,CAAC,CAAC,CAAC,CAAC,CAAC,CAAC,CAAC,CAAC,CAAC;AAC5B,CAAC,CAAC,CAAC,CAAC,CAAC,CAAC,CAAC,CAAC,CAAC,CAAC,CAAC,CAAC,CAAC,CAAC,CAAC,CAAC,CAAC,CAAC,CAAC,CAAC,CAAC,CAAC,CAAC,CAAC,CAAC,CAAC,CAAC,CAAC,CAAC,CAAC,CAAC,CAAC,CAAC,CAAC,CAAC,CAAC;AACpC,CAAC,CAAC,CAAC,CAAC,CAAC,CAAC,CAAC,CAAC,CAAC,CAAC,CAAC,CAAC,CAAC,CAAC,CAAC,CAAC,CAAC,CAAC,CAAC,CAAC,CAAC,CAAC,CAAC,CAAC,CAAC,CAAC,CAAC,CAAC,CAAC,CAAC,CAAC,CAAC,CAAC,CAAC,CAAC,CAAC,CAAC;AACrC,CAAC,CAAC,CAAC,CAAC,CAAC,CAAC,CAAC,CAAC,CAAC,CAAC,CAAC,CAAC,CAAC,CAAC,CAAC,CAAC,CAAC,CAAC,CAAC,CAAC,CAAC,CAAC,CAAC,CAAC,CAAC,CAAC,CAAC,CAAC,CAAC,CAAC,CAAC,CAAC,CAAC,CAAC;AAClC,CAAC,CAAC,CAAC,CAAC,CAAC,CAAC,CAAC,CAAC,CAAC,CAAC,CAAC,CAAC,CAAC,CAAC,CAAC,CAAC,CAAC,CAAC,CAAC,CAAC,CAAC,CAAC,CAAC,CAAC,CAAC,CAAC,CAAC,CAAC,CAAC,CAAC,CAAC,CAAC,CAAC,CAAC,CAAC,CAAC,CAAC,CAAC,CAAC,CAAC,CAAC,CAAC,CAAC,CAAC;AAC5C,CAAC,CAAC,CAAC,CAAC,CAAC,CAAC,CAAC,CAAC,CAAC,CAAC,CAAC,CAAC,CAAC,CAAC,CAAC,CAAC,CAAC,CAAC,CAAC,CAAC,CAAC,CAAC,CAAC,CAAC,CAAC,CAAC,CAAC,CAAC,CAAC,CAAC,CAAC,CAAC,CAAC,CAAC,CAAC,CAAC,CAAC,CAAC,CAAC,CAAC,CAAC,CAAC,CAAC,CAAC,CAAC,CAAC,CAAC,CAAC,CAAC,CAAC,CAAC,CAAC,CAAC,CAAC,CAAC,CAAC,CAAC,CAAC,CAAC,CAAC,CAAC,CAAC,CAAC,CAAC,CAAC,CAAC,CAAC,CAAC,CAAC,CAAC,CAAC,CAAC,CAAC,CAAC,CAAC,CAAC,CAAC,CAAC,CAAC,CAAC,CAAC,CAAC,CAAC,CAAC,CAAC,CAAC,CAAC,CAAC,CAAC,CAAC,CAAC,CAAC,CAAC,CAAC,CAAC,CAAC,CAAC,CAAC,CAAC,CAAC,CAAC,CAAC,CAAC;AACvG,CAAC,CAAC,CAAC,CAAC,CAAC,CAAC,CAAC,CAAC,CAAC,CAAC,CAAC,CAAC,CAAC,CAAC,CAAC,CAAC,CAAC,CAAC,CAAC,CAAC,CAAC,CAAC,CAAC,CAAC,CAAC,CAAC,CAAC,CAAC;AAC5B,CAAC,CAAC,CAAC,CAAC,CAAC,CAAC,CAAC,CAAC,CAAC,CAAC,CAAC,CAAC,CAAC,CAAC,CAAC,CAAC,CAAC,CAAC,CAAC,CAAC,CAAC,CAAC,CAAC,CAAC,CAAC,CAAC,CAAC,CAAC,CAAC,CAAC,CAAC,CAAC,CAAC,CAAC,CAAC,CAAC;AACpC,CAAC,CAAC,CAAC,CAAC,CAAC,CAAC,CAAC,CAAC,CAAC,CAAC,CAAC,CAAC,CAAC,CAAC,CAAC,CAAC,CAAC,CAAC,CAAC,CAAC,CAAC,CAAC,CAAC,CAAC,CAAC,CAAC,CAAC,CAAC,CAAC,CAAC,CAAC,CAAC,CAAC,CAAC,CAAC,CAAC,CAAC;AACrC,CAAC,CAAC,CAAC,CAAC,CAAC,CAAC,CAAC,CAAC,CAAC,CAAC,CAAC,CAAC,CAAC,CAAC,CAAC,CAAC,CAAC,CAAC,CAAC,CAAC,CAAC,CAAC,CAAC,CAAC,CAAC,CAAC,CAAC,CAAC,CAAC,CAAC,CAAC,CAAC,CAAC,CAAC,CAAC,CAAC,CAAC,CAAC,CAAC,CAAC;AACxC,CAAC,CAAC,CAAC,CAAC,CAAC,CAAC,CAAC,CAAC,CAAC,CAAC,CAAC,CAAC,CAAC,CAAC,CAAC,CAAC,CAAC,CAAC,CAAC,CAAC,CAAC,CAAC,CAAC,CAAC,CAAC,CAAC,CAAC,CAAC,CAAC,CAAC,CAAC,CAAC,CAAC,CAAC,CAAC,CAAC,CAAC,CAAC,CAAC,CAAC,CAAC,CAAC,CAAC,CAAC,CAAC,CAAC,CAAC,CAAC,CAAC,CAAC,CAAC,CAAC,CAAC,CAAC,CAAC,CAAC,CAAC;AACzD,CAAC,CAAC,CAAC,CAAC,CAAC,CAAC,CAAC,CAAC,CAAC,CAAC,CAAC,CAAC,CAAC,CAAC,CAAC,CAAC,CAAC,CAAC,CAAC,CAAC,CAAC,CAAC,CAAC,CAAC,CAAC,CAAC,CAAC,CAAC,CAAC,CAAC,CAAC,CAAC,CAAC,CAAC,CAAC,CAAC,CAAC,CAAC,CAAC,CAAC,CAAC,CAAC,CAAC,CAAC,CAAC,CAAC,CAAC,CAAC,CAAC,CAAC,CAAC,CAAC,CAAC,CAAC,CAAC,CAAC,CAAC,CAAC,CAAC,CAAC,CAAC,CAAC,CAAC,CAAC,CAAC,CAAC,CAAC,CAAC,CAAC,CAAC,CAAC,CAAC,CAAC,CAAC,CAAC,CAAC,CAAC,CAAC,CAAC,CAAC,CAAC,CAAC,CAAC,CAAC,CAAC,CAAC,CAAC,CAAC,CAAC,CAAC,CAAC,CAAC,CAAC,CAAC,CAAC,CAAC,CAAC,CAAC,CAAC,CAAC,CAAC,CAAC,CAAC,CAAC,CAAC,CAAC,CAAC,CAAC,CAAC,CAAC,CAAC,CAAC,CAAC,CAAC,CAAC,CAAC;AACpH,CAAC,CAAC,CAAC,CAAC,CAAC,CAAC,CAAC,CAAC,CAAC,CAAC,CAAC,CAAC,CAAC,CAAC,CAAC,CAAC,CAAC,CAAC,CAAC,CAAC,CAAC,CAAC,CAAC,CAAC,CAAC,CAAC,CAAC,CAAC;AAC5B,CAAC,CAAC,CAAC,CAAC,CAAC,CAAC,CAAC,CAAC,CAAC,CAAC,CAAC,CAAC,CAAC,CAAC,CAAC,CAAC,CAAC,CAAC,CAAC,CAAC,CAAC,CAAC,CAAC,CAAC,CAAC,CAAC,CAAC,CAAC,CAAC,CAAC,CAAC,CAAC,CAAC,CAAC,CAAC,CAAC;AACpC,CAAC,CAAC,CAAC,CAAC,CAAC,CAAC,CAAC,CAAC,CAAC,CAAC,CAAC,CAAC,CAAC,CAAC,CAAC,CAAC,CAAC,CAAC,CAAC,CAAC,CAAC,CAAC,CAAC,CAAC,CAAC,CAAC,CAAC,CAAC,CAAC,CAAC,CAAC,CAAC,CAAC,CAAC,CAAC,CAAC,CAAC,CAAC,CAAC,CAAC;AACxC,CAAC,CAAC,CAAC,CAAC,CAAC,CAAC,CAAC,CAAC,CAAC,CAAC,CAAC,CAAC,CAAC,CAAC,CAAC,CAAC,CAAC,CAAC,CAAC,CAAC,CAAC,CAAC,CAAC,CAAC,CAAC,CAAC,CAAC,CAAC,CAAC,CAAC,CAAC,CAAC,CAAC,CAAC,CAAC,CAAC,CAAC,CAAC;AACtC,CAAC,CAAC,CAAC,CAAC,CAAC,CAAC,CAAC,CAAC,CAAC,CAAC,CAAC,CAAC,CAAC,CAAC,CAAC,CAAC,CAAC,CAAC,CAAC,CAAC,CAAC,CAAC,CAAC,CAAC,CAAC,CAAC,CAAC,CAAC,CAAC,CAAC,CAAC,CAAC;AAChC,CAAC,CAAC,CAAC,CAAC,CAAC,CAAC,CAAC,CAAC,CAAC,CAAC,CAAC,CAAC;AACZ,CAAC,CAAC,CAAC,CAAC,CAAC,CAAC,CAAC,CAAC,CAAC,CAAC,CAAC,CAAC,CAAC,CAAC,CAAC,CAAC,CAAC,CAAC,CAAC,CAAC,CAAC,CAAC,CAAC,CAAC,CAAC,CAAC,CAAC,CAAC,CAAC,CAAC,CAAC,CAAC,CAAC,CAAC,CAAC;AACnC,CAAC,CAAC,CAAC,CAAC,CAAC,CAAC,CAAC,CAAC,CAAC,CAAC,CAAC,CAAC,CAAC,CAAC,CAAC,CAAC,CAAC,CAAC,CAAC,CAAC,CAAC,CAAC,CAAC,CAAC,CAAC,CAAC,CAAC,CAAC,CAAC,CAAC,CAAC,CAAC,CAAC,CAAC,CAAC,CAAC,CAAC,CAAC,CAAC,CAAC,CAAC,CAAC,CAAC,CAAC,CAAC,CAAC,CAAC,CAAC,CAAC,CAAC,CAAC,CAAC,CAAC,CAAC,CAAC,CAAC,CAAC,CAAC,CAAC,CAAC,CAAC,CAAC,CAAC,CAAC,CAAC,CAAC,CAAC,CAAC,CAAC,CAAC,CAAC,CAAC,CAAC,CAAC,CAAC,CAAC,CAAC,CAAC,CAAC,CAAC,CAAC,CAAC,CAAC,CAAC,CAAC,CAAC,CAAC,CAAC,CAAC,CAAC,CAAC,CAAC,CAAC,CAAC,CAAC,CAAC,CAAC,CAAC,CAAC,CAAC,CAAC,CAAC,CAAC,CAAC,CAAC,CAAC,CAAC,CAAC,CAAC,CAAC,CAAC,CAAC,CAAC,CAAC,CAAC,CAAC,CAAC,CAAC,CAAC,CAAC,CAAC,CAAC,CAAC,CAAC,CAAC,CAAC,CAAC,CAAC,CAAC,CAAC,CAAC,CAAC,CAAC,CAAC,CAAC,CAAC,CAAC,CAAC,CAAC,CAAC,CAAC,CAAC,CAAC,CAAC,CAAC,CAAC,CAAC,CAAC,CAAC,CAAC,CAAC,CAAC,CAAC,CAAC,CAAC,CAAC,CAAC,CAAC,CAAC,CAAC,CAAC,CAAC,CAAC,CAAC,CAAC,CAAC,CAAC,CAAC,CAAC,CAAC,CAAC;AAC3K,CAAC,CAAC,CAAC,CAAC,CAAC,CAAC,CAAC,CAAC,CAAC,CAAC,CAAC,CAAC,CAAC,CAAC,CAAC,CAAC,CAAC,CAAC,CAAC,CAAC,CAAC,CAAC,CAAC,CAAC,CAAC,CAAC,CAAC,CAAC,CAAC,CAAC,CAAC,CAAC,CAAC,CAAC,CAAC,CAAC,CAAC,CAAC,CAAC,CAAC;AACxC,CAAC,CAAC,CAAC,CAAC,CAAC,CAAC,CAAC,CAAC,CAAC,CAAC,CAAC,CAAC,CAAC,CAAC,CAAC,CAAC,CAAC,CAAC,CAAC,CAAC,CAAC,CAAC,CAAC,CAAC,CAAC,CAAC,CAAC,CAAC,CAAC,CAAC;AAC9B,CAAC,CAAC,CAAC,CAAC,CAAC,CAAC,CAAC,CAAC,CAAC,CAAC,CAAC,CAAC,CAAC,CAAC,CAAC,CAAC,CAAC,CAAC,CAAC,CAAC,CAAC,CAAC,CAAC,CAAC,CAAC,CAAC,CAAC,CAAC,CAAC,CAAC;AAC9B,CAAC,CAAC,CAAC,CAAC,CAAC,CAAC,CAAC,CAAC,CAAC,CAAC,CAAC,CAAC,CAAC,CAAC,CAAC,CAAC,CAAC,CAAC,CAAC,CAAC,CAAC,CAAC,CAAC,CAAC,CAAC,CAAC,CAAC,CAAC,CAAC;AAC7B,CAAC,CAAC,CAAC,CAAC,CAAC,CAAC,CAAC,CAAC,CAAC,CAAC,CAAC,CAAC,CAAC,CAAC,CAAC,CAAC,CAAC,CAAC,CAAC,CAAC,CAAC,CAAC,CAAC,CAAC,CAAC,CAAC,CAAC,CAAC,CAAC,CAAC;AAC9B,CAAC,CAAC,CAAC,CAAC,CAAC,CAAC,CAAC,CAAC,CAAC,CAAC,CAAC,CAAC,CAAC,CAAC,CAAC,CAAC;AAChB,CAAC,CAAC,CAAC,CAAC,CAAC,CAAC,CAAC,CAAC,CAAC,CAAC,CAAC,CAAC,CAAC,CAAC,CAAC;AACf,CAAC,CAAC,CAAC,CAAC,CAAC,CAAC,CAAC,CAAC,CAAC,CAAC,CAAC,CAAC,CAAC;AACb,CAAC,CAAC,CAAC,CAAC,CAAC,CAAC,CAAC,CAAC,CAAC,CAAC,CAAC,CAAC,CAAC,CAAC;AACd,CAAC,CAAC,CAAC,CAAC,CAAC,CAAC,CAAC,CAAC,CAAC,CAAC;AACV,CAAC,CAAC,CAAC,CAAC,CAAC,CAAC,CAAC,CAAC,CAAC;AACT,CAAC,CAAC,CAAC,CAAC,CAAC,CAAC;AACN,CAAC,CAAC,CAAC;AACH,CAAC,CAAC,CAAC;"
      }
    },
    {
      "name": "unctx:transform",
      "start": 1726490134212,
      "end": 1726490134212,
      "order": "post"
    },
    {
      "name": "nuxt:pages-macros-transform",
      "start": 1726490134212,
      "end": 1726490134212,
      "order": "post"
    },
    {
      "name": "nuxt:runtime-paths-dep",
      "start": 1726490134212,
      "end": 1726490134212,
      "order": "post"
    },
    {
      "name": "nuxt:route-injection-plugin",
      "start": 1726490134212,
      "end": 1726490134212,
      "order": "post"
    },
    {
      "name": "nuxt:components-loader",
      "start": 1726490134213,
      "end": 1726490134213,
      "order": "post"
    },
    {
      "name": "nuxt:tree-shake-composables:transform",
      "start": 1726490134213,
      "end": 1726490134213,
      "order": "post"
    },
    {
      "name": "vite:build-import-analysis",
      "start": 1726490134213,
      "end": 1726490134214,
      "order": "normal"
    },
    {
      "name": "vite:reporter",
      "start": 1726490134214,
      "end": 1726490134214,
      "order": "normal"
    }
  ]
}
