{
  "resolvedId": "/home/saeed/w/projects/beautymap/beautyfront/components/icons/DeleteAccountIcon.vue",
  "transforms": [
    {
      "name": "vite:load-fallback",
      "result": "<template>\r\n  <svg width=\"20\" height=\"20\" viewBox=\"0 0 20 20\" fill=\"none\" xmlns=\"http://www.w3.org/2000/svg\">\r\n    <path d=\"M1 19V18C1 15.7909 2.79086 14 5 14H9C11.2091 14 13 15.7909 13 18V19\" stroke=\"#133C3E\" stroke-width=\"2\" stroke-linecap=\"round\"/>\r\n    <path d=\"M7 11C5.34315 11 4 9.6569 4 8C4 6.34315 5.34315 5 7 5C8.6569 5 10 6.34315 10 8C10 9.6569 8.6569 11 7 11Z\" stroke=\"#133C3E\" stroke-width=\"2\" stroke-linecap=\"round\"/>\r\n    <path d=\"M13 1L19 7\" stroke=\"#133C3E\" stroke-width=\"2\" stroke-linecap=\"round\"/>\r\n    <path d=\"M19 1L13 7\" stroke=\"#133C3E\" stroke-width=\"2\" stroke-linecap=\"round\"/>\r\n  </svg>\r\n</template>\r\n",
      "start": 1726488542740,
      "end": 1726488542892,
      "sourcemaps": null
    },
    {
      "name": "nuxt:layer-aliasing",
      "start": 1726488542892,
      "end": 1726488542892,
      "order": "pre"
    },
    {
      "name": "nuxt:server-devonly:transform",
      "start": 1726488542892,
      "end": 1726488542893,
      "order": "pre"
    },
    {
      "name": "nuxt:client-fallback-auto-id",
      "start": 1726488542893,
      "end": 1726488542893,
      "order": "pre"
    },
    {
      "name": "vite:css",
      "start": 1726488542893,
      "end": 1726488542893,
      "order": "normal"
    },
    {
      "name": "vite:esbuild",
      "start": 1726488542893,
      "end": 1726488542893,
      "order": "normal"
    },
    {
      "name": "vite:json",
      "start": 1726488542893,
      "end": 1726488542893,
      "order": "normal"
    },
    {
      "name": "vite:worker",
      "start": 1726488542893,
      "end": 1726488542893,
      "order": "normal"
    },
    {
      "name": "vite:vue",
      "result": "const _sfc_main = {}\nimport { createElementVNode as _createElementVNode, openBlock as _openBlock, createElementBlock as _createElementBlock } from \"vue\"\n\nconst _hoisted_1 = {\n  width: \"20\",\n  height: \"20\",\n  viewBox: \"0 0 20 20\",\n  fill: \"none\",\n  xmlns: \"http://www.w3.org/2000/svg\"\n}\nconst _hoisted_2 = /*#__PURE__*/_createElementVNode(\"path\", {\n  d: \"M1 19V18C1 15.7909 2.79086 14 5 14H9C11.2091 14 13 15.7909 13 18V19\",\n  stroke: \"#133C3E\",\n  \"stroke-width\": \"2\",\n  \"stroke-linecap\": \"round\"\n}, null, -1)\nconst _hoisted_3 = /*#__PURE__*/_createElementVNode(\"path\", {\n  d: \"M7 11C5.34315 11 4 9.6569 4 8C4 6.34315 5.34315 5 7 5C8.6569 5 10 6.34315 10 8C10 9.6569 8.6569 11 7 11Z\",\n  stroke: \"#133C3E\",\n  \"stroke-width\": \"2\",\n  \"stroke-linecap\": \"round\"\n}, null, -1)\nconst _hoisted_4 = /*#__PURE__*/_createElementVNode(\"path\", {\n  d: \"M13 1L19 7\",\n  stroke: \"#133C3E\",\n  \"stroke-width\": \"2\",\n  \"stroke-linecap\": \"round\"\n}, null, -1)\nconst _hoisted_5 = /*#__PURE__*/_createElementVNode(\"path\", {\n  d: \"M19 1L13 7\",\n  stroke: \"#133C3E\",\n  \"stroke-width\": \"2\",\n  \"stroke-linecap\": \"round\"\n}, null, -1)\nconst _hoisted_6 = [\n  _hoisted_2,\n  _hoisted_3,\n  _hoisted_4,\n  _hoisted_5\n]\n\nfunction _sfc_render(_ctx, _cache) {\n  return (_openBlock(), _createElementBlock(\"svg\", _hoisted_1, _hoisted_6))\n}\n\n\nimport _export_sfc from '\u0000plugin-vue:export-helper'\nexport default /*#__PURE__*/_export_sfc(_sfc_main, [['render',_sfc_render]])",
      "start": 1726488542893,
      "end": 1726488542893,
      "order": "normal",
      "sourcemaps": {
        "mappings": ""
      }
    },
    {
      "name": "vite:vue-jsx",
      "start": 1726488542893,
      "end": 1726488542893,
      "order": "normal"
    },
    {
      "name": "replace",
      "start": 1726488542893,
      "end": 1726488542893,
      "order": "normal"
    },
    {
      "name": "nuxt:remove-plugin-metadata",
      "start": 1726488542893,
      "end": 1726488542893,
      "order": "normal"
    },
    {
      "name": "nuxt:chunk-error",
      "start": 1726488542893,
      "end": 1726488542893,
      "order": "normal"
    },
    {
      "name": "nuxt:components:imports",
      "start": 1726488542893,
      "end": 1726488542893,
      "order": "normal"
    },
    {
      "name": "replace",
      "start": 1726488542893,
      "end": 1726488542893,
      "order": "normal"
    },
    {
      "name": "ssr-styles",
      "start": 1726488542893,
      "end": 1726488542893,
      "order": "normal"
    },
    {
      "name": "vite:define",
      "start": 1726488542893,
      "end": 1726488542893,
      "order": "normal"
    },
    {
      "name": "vite:css-post",
      "start": 1726488542893,
      "end": 1726488542893,
      "order": "normal"
    },
    {
      "name": "vite:build-html",
      "start": 1726488542893,
      "end": 1726488542893,
      "order": "normal"
    },
    {
      "name": "vite:worker-import-meta-url",
      "start": 1726488542893,
      "end": 1726488542893,
      "order": "normal"
    },
    {
      "name": "vite:asset-import-meta-url",
      "start": 1726488542893,
      "end": 1726488542893,
      "order": "normal"
    },
    {
      "name": "commonjs",
      "start": 1726488542893,
      "end": 1726488542893,
      "order": "normal"
    },
    {
      "name": "vite:dynamic-import-vars",
      "start": 1726488542893,
      "end": 1726488542893,
      "order": "normal"
    },
    {
      "name": "vite:import-glob",
      "start": 1726488542893,
      "end": 1726488542893,
      "order": "normal"
    },
    {
      "name": "nuxt:composable-keys",
      "start": 1726488542893,
      "end": 1726488542893,
      "order": "post"
    },
    {
      "name": "nuxt:imports-transform",
      "start": 1726488542893,
      "end": 1726488542894,
      "order": "post"
    },
    {
      "name": "unctx:transform",
      "start": 1726488542894,
      "end": 1726488542894,
      "order": "post"
    },
    {
      "name": "nuxt:pages-macros-transform",
      "start": 1726488542894,
      "end": 1726488542894,
      "order": "post"
    },
    {
      "name": "nuxt:runtime-paths-dep",
      "start": 1726488542894,
      "end": 1726488542894,
      "order": "post"
    },
    {
      "name": "nuxt:route-injection-plugin",
      "start": 1726488542894,
      "end": 1726488542894,
      "order": "post"
    },
    {
      "name": "nuxt:components-loader",
      "start": 1726488542894,
      "end": 1726488542894,
      "order": "post"
    },
    {
      "name": "nuxt:tree-shake-composables:transform",
      "start": 1726488542894,
      "end": 1726488542894,
      "order": "post"
    },
    {
      "name": "vite:build-import-analysis",
      "start": 1726488542894,
      "end": 1726488542894,
      "order": "normal"
    },
    {
      "name": "vite:reporter",
      "start": 1726488542894,
      "end": 1726488542894,
      "order": "normal"
    }
  ]
}
